{"data": {
"83695": {"id":"83695","name":"Poison Ivy Bistro","details":"100 Neo Tiew Road\nBollywood Veggies\nSingapore 719026","categories":["Pet-Friendly","Cafes & Coffee","Nasi Lemak","Healthy","Local Delights","Breakfast & Brunch","Vegetarian"],"featuredImages":["https://burpple.imgix.net/foods/1660192375_review_image1947522_original.?w=400&h=400&fit=crop&q=80&auto=format","https://burpple-3.imgix.net/foods/2ed12126a854c94c216e1936569_original.?w=400&h=400&fit=crop&q=80&auto=format","https://burpple-3.imgix.net/foods/32f07c8801d4cf3b6f121887395_original.?w=400&h=400&fit=crop&q=80&auto=format","https://burpple.imgix.net/foods/31b38ed1f6cd2566ef921884896_original.?w=400&h=400&fit=crop&q=80&auto=format","https://burpple-1.imgix.net/foods/330bd052e80e8d0d5c6c1884716_original.?w=400&h=400&fit=crop&q=80&auto=format"],"location":{"latitude":"1.4183191","longitude":"103.7168531"},"venueUrl":"https://www.burpple.com/bollywood-veggies","googleMapUrl":"https://www.google.com/maps/search/?api=1&query=1.4183191,103.7168531","openingHours":"Tuesday: 08:00am - 04:00pm\nWednesday: 08:00am - 04:00pm\nThursday: 08:00am - 04:00pm\nFriday: 08:00am - 04:00pm\nSaturday: 07:00am - 04:00pm\nSunday: 07:00am - 04:00pm\nMonday: 08:00am - 04:00pm"}
,"85368": {"id":"85368","name":"The Cheese Ark","details":"49 Stirling Road\n#01-489\nSingapore 141049","categories":["European"],"featuredImages":["https://burpple-3.imgix.net/foods/43e676bbfc0d8a9e8841912083_original.?w=400&h=400&fit=crop&q=80&auto=format","https://burpple-3.imgix.net/foods/2fba1bb72ba736c7716c1898248_original.?w=400&h=400&fit=crop&q=80&auto=format","https://burpple-2.imgix.net/foods/6128d3777aadf89641a1865448_original.?w=400&h=400&fit=crop&q=80&auto=format","https://burpple.imgix.net/foods/a5819e11cf707832a1818080_original.?w=400&h=400&fit=crop&q=80&auto=format","https://burpple-1.imgix.net/foods/30b0db3c306fecbdac701786736_original.?w=400&h=400&fit=crop&q=80&auto=format"],"location":{"latitude":"1.2975294","longitude":"103.8022686"},"venueUrl":"https://www.burpple.com/the-cheese-ark","googleMapUrl":"https://www.google.com/maps/search/?api=1&query=1.2975294,103.8022686","openingHours":"Tuesday: 11:00am - 09:00pm\nWednesday: 11:00am - 09:00pm\nThursday: 11:00am - 09:00pm\nFriday: 11:00am - 09:00pm\nSaturday: 11:00am - 09:00pm\nSunday: 11:00am - 09:00pm\nMonday: Closed"}
,"215452": {"id":"215452","name":"Zazz Pizza (Cross Street Exchange)","details":"18 Cross Street\n#01-108 Cross Street Exchange\nSingapore 048423","categories":["Italian","Pizza","Pasta"],"featuredImages":["https://burpple-3.imgix.net/foods/1657517650_review_image1944328_original.?w=400&h=400&fit=crop&q=80&auto=format","https://burpple-3.imgix.net/foods/1656819182_review_image1943600_original.?w=400&h=400&fit=crop&q=80&auto=format","https://burpple-1.imgix.net/foods/2f5bf3634d9e19b22b521915853_original.?w=400&h=400&fit=crop&q=80&auto=format","https://burpple.imgix.net/foods/36a9dad6a3f4b7e31261892472_original.?w=400&h=400&fit=crop&q=80&auto=format","https://burpple-2.imgix.net/foods/140876b355ec5744f481871893_original.?w=400&h=400&fit=crop&q=80&auto=format"],"location":{"latitude":"1.2835867","longitude":"103.8470853"},"venueUrl":"https://www.burpple.com/zazz-pizza","googleMapUrl":"https://www.google.com/maps/search/?api=1&query=1.2835867,103.8470853","openingHours":"Tuesday: 12:00pm - 02:30pm, 05:30pm - 10:30pm\nWednesday: 12:00pm - 02:30pm, 05:30pm - 10:30pm\nThursday: 12:00pm - 02:30pm, 05:30pm - 10:30pm\nFriday: 12:00pm - 02:30pm, 05:30pm - 10:30pm\nSaturday: 11:30am - 10:30pm\nSunday: 11:30am - 10:00pm\nMonday: 12:00pm - 02:30pm, 05:30pm - 10:30pm"}
,"207298": {"id":"207298","name":"So France (DUO Galleria)","details":"7 Fraser Street\n#01-51/56 DUO Galleria\nSingapore 189356","categories":["French","Cafes & Coffee","Breakfast & Brunch","Dinner with Drinks"],"featuredImages":["https://burpple-2.imgix.net/foods/1667117500_review_image1954140_original.?w=400&h=400&fit=crop&q=80&auto=format","https://burpple-2.imgix.net/foods/1653717178_review_image1939996_original.?w=400&h=400&fit=crop&q=80&auto=format","https://burpple-2.imgix.net/foods/2f5ed8763f3ea2bcaa801917140_original.?w=400&h=400&fit=crop&q=80&auto=format","https://burpple-3.imgix.net/foods/2f21e9d36646abf8e13a1891932_original.?w=400&h=400&fit=crop&q=80&auto=format","https://burpple.imgix.net/foods/2f21e9d36645a69d01f81891931_original.?w=400&h=400&fit=crop&q=80&auto=format"],"location":{"latitude":"1.2991754","longitude":"103.8579486"},"venueUrl":"https://www.burpple.com/so-france","googleMapUrl":"https://www.google.com/maps/search/?api=1&query=1.2991754,103.8579486","openingHours":"Tuesday: 08:00am - 09:00pm\nWednesday: 08:00am - 09:00pm\nThursday: 08:00am - 09:00pm\nFriday: 08:00am - 10:00pm\nSaturday: 09:00am - 10:00pm\nSunday: 09:00am - 09:00pm\nMonday: 08:00am - 09:00pm"}
}, "end": "2023-02-13T18:00:56.000Z" }
